{
  "mcpServers": {
    "supabase": {
      "command": "npx",
      "args": [
        "-y",
        "@supabase/mcp-server-supabase@latest"
      ],
      "env": {
        "SUPABASE_ACCESS_TOKEN": "${{ secrets.SUPABASE_ACCESS_TOKEN }}",
        "SUPABASE_PROJECT_REF": "${{ secrets.SUPABASE_PROJECT_REF }}"
      },
      "disabled": false,
      "autoApprove": [
        "list_projects",
        "list_tables",
        "execute_sql",
        "apply_migration"
      ]
    },
    "context7": {
      "command": "npx",
      "args": [
        "-y",
        "@upstash/context7-mcp@latest"
      ],
      "disabled": false,
      "autoApprove": []
    },
    "TestSprite": {
      "command": "npx",
      "args": [
        "@testsprite/testsprite-mcp@latest"
      ],
      "env": {
        "API_KEY": "${{ secrets.TESTSPRITE_API_KEY }}"
      },
      "disabled": false,
      "autoApprove": [
        "testsprite_bootstrap_tests"
      ]
    }
  }
}